README.md
setup.cfg
setup.py
nflsim/__init__.py
nflsim/core.py
nflsim/gamedata.py
nflsim/pwr.py
nflsim/regression.py
nflsim/simulate.py
nflsim/teams.py
nflsim/tiebreak.py
nflsim/util.py
nflsim.egg-info/PKG-INFO
nflsim.egg-info/SOURCES.txt
nflsim.egg-info/dependency_links.txt
nflsim.egg-info/requires.txt
nflsim.egg-info/top_level.txt