Metadata-Version: 2.1
Name: nflsim
Version: 1.1.1
Summary: A tool for simulating the NFL regular season and playoffs
Home-page: https://github.com/dmparker0/nflsim/
Author: Dan Parker
Author-email: dan.m.parker0@gmail.com
License: MIT
Download-URL: https://github.com/dmparker0/nflsim/archive/v1.1.1.tar.gz
Keywords: NFL,football,sports,simulation,statistics
Platform: UNKNOWN
